{
  "indications": [
    "Профилактика венозной тромбоэмболии после планового эндопротезирования тазобедренного или коленного сустава [I82.9]",
    "Профилактика инсульта и системной тромбоэмболии при неклапанной фибрилляции предсердий [I48]",
    "Тромбоз глубоких вен [I80.2]",
    "Тромбоэмболия легочной артерии [I26]",
    "Профилактика рецидивов тромбоза глубоких вен [I80.2]",
    "Профилактика рецидивов тромбоэмболии легочной артерии [I26]"
  ],
  "dosage": [
    {
      "tags": "adult; Профилактика венозной тромбоэмболии после планового эндопротезирования тазобедренного или коленного сустава [I82.9]",
      "indication": {
        "step1": {
          "dose": 2.5,
          "unit": "мг",
          "interval": 1,
          "intervalUnit": "DAY",
          "intakeCount": 2,
          "daily_dose": 5,
          "courseDurationMin": "P32D",
          "courseDurationMax": "P38D",
          "courseMaxF": {
            "expr": "daily_dose*38",
            "vars": [
              "daily_dose"
            ]
          }
        },
        "step2": {
          "dose": 2.5,
          "unit": "мг",
          "interval": 1,
          "intervalUnit": "DAY",
          "intakeCount": 2,
          "daily_dose": 5,
          "courseDurationMin": "P10D",
          "courseDurationMax": "P14D",
          "courseMaxF": {
            "expr": "daily_dose*14",
            "vars": [
              "daily_dose"
            ]
          }
        },
        "schemaDescription": "У пациентов после планового эндопротезирования тазобедренного или коленного сустава: 2,5 мг 2 раза в сутки (первый прием через 12-24 ч после оперативного вмешательства). У пациентов, перенесших эндопротезирование тазобедренного сустава, рекомендуемая длительность терапии составляет от 32 до 38 дней, коленного сустава от 10 до 14 дней."
      }
    },
    {
      "tags": "adult; Фибрилляция предсердий [I48]",
      "indication": {
        "dose": 5,
        "unit": "мг",
        "interval": 1,
        "intervalUnit": "DAY",
        "intakeCount": 2,
        "daily_dose": 10,
        "schemaDescription": "У пациентов с фибрилляцией предсердий: по 5 мг два раза в сутки. Терапию следует продолжать длительное время."
      }
    },
    {
      "tags": "adult; Фибрилляция предсердий [I48]; if: сочетание двух или более характеристик (возраст 80 лет и старше, масса тела 60 кг и менее, концентрация креатинина ≥ 1,5 мг/дл)",
      "indication": {
        "dose": 2.5,
        "unit": "мг",
        "interval": 1,
        "intervalUnit": "DAY",
        "intakeCount": 2,
        "daily_dose": 5,
        "schemaDescription": "У пациентов с фибрилляцией предсердий дозу препарата снижают до 2,5 мг два раза в сутки при наличии сочетания двух или более из следующих характеристик: возраст 80 лет и старше, масса тела 60 кг и менее или концентрация креатинина в плазме крови ≥ 1,5 мг/дл (133 мкмоль/л)."
      }
    },
    {
      "tags": "adult; Тромбоз глубоких вен [I80.2]; Тромбоэмболия легочной артерии [I26]",
      "indication": {
        "step1": {
          "startDosage": 10,
          "dose": 10,
          "unit": "мг",
          "interval": 1,
          "intervalUnit": "DAY",
          "intakeCount": 2,
          "daily_dose": 20,
          "courseDurationMin": "P7D",
          "courseDurationMax": "P7D",
          "courseMaxF": {
            "expr": "daily_dose*7",
            "vars": [
              "daily_dose"
            ]
          }
        },
        "step2": {
          "dose": 5,
          "unit": "мг",
          "interval": 1,
          "intervalUnit": "DAY",
          "intakeCount": 2,
          "daily_dose": 10,
          "courseDurationMin": "P3M",
          "courseMaxF": {
            "expr": "daily_dose*90",
            "vars": [
              "daily_dose"
            ]
          }
        },
        "schemaDescription": "Лечение тромбоза глубоких вен, тромбоэмболии легочной артерии (ТЭЛА): по 10 мг два раза в сутки в течение 7 дней, затем 5 мг 2 раза в сутки. ... составляя, как минимум, 3 месяца."
      }
    },
    {
      "tags": "adult; Профилактика рецидивов тромбоза глубоких вен [I80.2]; Профилактика рецидивов тромбоэмболии легочной артерии [I26]",
      "indication": {
        "dose": 2.5,
        "unit": "мг",
        "interval": 1,
        "intervalUnit": "DAY",
        "intakeCount": 2,
        "daily_dose": 5,
        "schemaDescription": "Профилактика рецидивов тромбоза глубоких вен, тромбоэмболии легочной артерии (ТЭЛА): по 2,5 мг два раза в сутки после, как минимум, 6 месяцев лечения тромбоза глубоких вен или ТЭЛА апиксабаном в дозе 5 мг два раза в сутки или другим антикоагулянтом."
      }
    },
    {
      "tags": "adult; Фибрилляция предсердий [I48]; if: кардиоверсия, пациент ранее не получал антикоагулянты",
      "indication": {
        "dose": 5,
        "unit": "мг",
        "interval": 1,
        "intervalUnit": "DAY",
        "intakeCount": 2,
        "daily_dose": 10,
        "courseDurationMin": "P3D",
        "courseDurationMax": "P3D",
        "courseMaxF": {
          "expr": "daily_dose*3",
          "vars": [
            "daily_dose"
          ]
        },
        "schemaDescription": "Пациентам, не проходившим лечение антикоагулянтами, перед проведением кардиоверсии необходимо назначить по крайней мере 5 доз препарата АПИКСАБАН по 5 мг два раза в сутки (по 2,5 мг два раза в сутки для пациентов, которым требуется уменьшение дозы) для достижения адекватной антикоагуляции."
      }
    },
    {
      "tags": "adult; Фибрилляция предсердий [I48]; if: кардиоверсия, требуется уменьшение дозы",
      "indication": {
        "dose": 2.5,
        "unit": "мг",
        "interval": 1,
        "intervalUnit": "DAY",
        "intakeCount": 2,
        "daily_dose": 5,
        "courseDurationMin": "P3D",
        "courseDurationMax": "P3D",
        "courseMaxF": {
          "expr": "daily_dose*3",
          "vars": [
            "daily_dose"
          ]
        },
        "schemaDescription": "Пациентам, не проходившим лечение антикоагулянтами, перед проведением кардиоверсии необходимо назначить по крайней мере 5 доз препарата АПИКСАБАН по 2,5 мг два раза в сутки для пациентов, которым требуется уменьшение дозы."
      }
    },
    {
      "tags": "adult; Фибрилляция предсердий [I48]; if: кардиоверсия, требуется проведение до назначения 5 доз",
      "indication": {
        "startDosage": 10,
        "dose": 5,
        "unit": "мг",
        "interval": 1,
        "intervalUnit": "DAY",
        "intakeCount": 2,
        "daily_dose": 10,
        "loading_dose": 10,
        "schemaDescription": "В случае если проведение кардиоверсии требуется до назначения 5 доз препарата АПИКСАБАН необходимо принять нагрузочную дозу в 10 мг с последующим приемом 5 мг два раза в сутки. Необходимо принять нагрузочную дозу, по крайней мере, за 2 часа до проведения кардиоверсии."
      }
    },
    {
      "tags": "adult; Фибрилляция предсердий [I48]; if: кардиоверсия, требуется проведение до 5 доз и пациент подходит под категорию для снижения дозы",
      "indication": {
        "startDosage": 5,
        "dose": 2.5,
        "unit": "мг",
        "interval": 1,
        "intervalUnit": "DAY",
        "intakeCount": 2,
        "daily_dose": 5,
        "loading_dose": 5,
        "schemaDescription": "Следует уменьшить нагрузочную дозу до 5 мг с последующим приемом 2,5 мг два раза в сутки, если пациент подходит под категорию для снижения дозы. Необходимо принять нагрузочную дозу, по крайней мере, за 2 часа до проведения кардиоверсии."
      }
    },
    {
      "tags": "old; Фибрилляция предсердий [I48]; if: клиренс креатинина 15-29 мл/мин",
      "indication": {
        "dose": 2.5,
        "unit": "мг",
        "interval": 1,
        "intervalUnit": "DAY",
        "intakeCount": 2,
        "daily_dose": 5,
        "schemaDescription": "У пациентов с нарушением функции почек тяжелой степени (с клиренсом креатинина 15-29 мл/мин) ... у пациентов с фибрилляцией предсердий следует применять дозу апиксабана 2,5 мг два раза в сутки."
      }
    }
  ],
  "administration": {
    "time": "",
    "food": "независимо от приема пищи",
    "form": "таблетка",
    "how": "перорально"
  }
}
